miner_toolbox/__init__.py
miner_toolbox/miner_toolbox.py
miner_toolbox-0.0.2.dist-info/METADATA
miner_toolbox-0.0.2.dist-info/WHEEL
miner_toolbox-0.0.2.dist-info/top_level.txt
miner_toolbox-0.0.2.dist-info/RECORD
