Metadata-Version: 2.1
Name: miner-toolbox
Version: 0.0.2
Summary: a pip-installable package example
Home-page: https://github.com/
Author: Michal Rovnanik
Author-email: rovnani.michal@gmail.com
License: MIT
Keywords: toolbox,utils
Platform: UNKNOWN
